IoTuring/__init__.py
IoTuring/__main__.py
IoTuring/ClassManager/ClassManager.py
IoTuring/ClassManager/consts.py
IoTuring/Configurator/Configuration.py
IoTuring/Configurator/Configurator.py
IoTuring/Configurator/ConfiguratorIO.py
IoTuring/Configurator/ConfiguratorLoader.py
IoTuring/Configurator/ConfiguratorObject.py
IoTuring/Configurator/MenuPreset.py
IoTuring/Configurator/messages.py
IoTuring/Entity/Entity.py
IoTuring/Entity/EntityData.py
IoTuring/Entity/EntityManager.py
IoTuring/Entity/Deployments/ActiveWindow/ActiveWindow.py
IoTuring/Entity/Deployments/AppInfo/AppInfo.py
IoTuring/Entity/Deployments/Battery/Battery.py
IoTuring/Entity/Deployments/BootTime/BootTime.py
IoTuring/Entity/Deployments/Cpu/Cpu.py
IoTuring/Entity/Deployments/DesktopEnvironment/DesktopEnvironment.py
IoTuring/Entity/Deployments/Disk/Disk.py
IoTuring/Entity/Deployments/DisplayMode/DisplayMode.py
IoTuring/Entity/Deployments/Fanspeed/Fanspeed.py
IoTuring/Entity/Deployments/FileSwitch/FileSwitch.py
IoTuring/Entity/Deployments/Hostname/Hostname.py
IoTuring/Entity/Deployments/Lock/Lock.py
IoTuring/Entity/Deployments/Monitor/Monitor.py
IoTuring/Entity/Deployments/Notify/Notify.py
IoTuring/Entity/Deployments/Notify/icon.png
IoTuring/Entity/Deployments/OperatingSystem/OperatingSystem.py
IoTuring/Entity/Deployments/Power/Power.py
IoTuring/Entity/Deployments/Ram/Ram.py
IoTuring/Entity/Deployments/Temperature/Temperature.py
IoTuring/Entity/Deployments/Terminal/Terminal.py
IoTuring/Entity/Deployments/Time/Time.py
IoTuring/Entity/Deployments/UpTime/UpTime.py
IoTuring/Entity/Deployments/Username/Username.py
IoTuring/Entity/Deployments/Volume/Volume.py
IoTuring/Entity/ToImplement/Brightness/Brightness.py
IoTuring/Entity/ToImplement/CpuTemperature/CpuTemperatures.py
IoTuring/Entity/ToImplement/Network/Network.py
IoTuring/Entity/ToImplement/Screenshot/Screenshot.py
IoTuring/Entity/ToImplement/State/State.py
IoTuring/Entity/ValueFormat/ValueFormatter.py
IoTuring/Entity/ValueFormat/ValueFormatterOptions.py
IoTuring-2024.6.1.dist-info/COPYING
IoTuring-2024.6.1.dist-info/METADATA
IoTuring-2024.6.1.dist-info/WHEEL
IoTuring-2024.6.1.dist-info/entry_points.txt
IoTuring-2024.6.1.dist-info/top_level.txt
IoTuring-2024.6.1.dist-info/RECORD
