Metadata-Version: 2.1
Name: IoTuring
Version: 2024.6.1
Summary: Simple and powerful cross-platform script to control your pc and share statistics using communication protocols like MQTT and home control hubs like HomeAssistant.
Author-email: richibrics <riccardo.briccola.dev@gmail.com>, infeeeee <gyetpet@mailbox.org>
Maintainer-email: richibrics <riccardo.briccola.dev@gmail.com>, infeeeee <gyetpet@mailbox.org>
License: GNU GENERAL PUBLIC LICENSE
Project-URL: homepage, https://github.com/richibrics/IoTuring
Project-URL: documentation, https://github.com/richibrics/IoTuring
Project-URL: repository, https://github.com/richibrics/IoTuring
Project-URL: changelog, https://github.com/richibrics/IoTuring/releases
Keywords: iot,mqtt,monitor
Classifier: Development Status :: 3 - Alpha
Classifier: Environment :: Console
Classifier: Programming Language :: Python
Classifier: Topic :: System :: Monitoring
Requires-Python: >=3.8
License-File: COPYING
Requires-Dist: paho-mqtt >=2.0.0
Requires-Dist: psutil
Requires-Dist: PyYAML
Requires-Dist: requests
Requires-Dist: InquirerPy
Requires-Dist: PyObjC ; sys_platform == "darwin"
Requires-Dist: IoTuring-applesmc ; sys_platform == "darwin"
Requires-Dist: tinyWinToast ; sys_platform == "win32"
Provides-Extra: test
Requires-Dist: pytest ; extra == 'test'
